mdconvertor_tools/__init__.py
mdconvertor_tools/md_to_html.py
mdconvertor_tools/libs/custom_css.css
mdconvertor_tools/libs/tailwind.min.css
mdconvertor_tools/libs/tex-mml-chtml.js
mdconvertor_tools-0.0.5.data/data/assets/custom_css.css
mdconvertor_tools-0.0.5.data/data/assets/tailwind.min.css
mdconvertor_tools-0.0.5.data/data/assets/tex-mml-chtml.js
mdconvertor_tools-0.0.5.dist-info/LICENSE
mdconvertor_tools-0.0.5.dist-info/METADATA
mdconvertor_tools-0.0.5.dist-info/WHEEL
mdconvertor_tools-0.0.5.dist-info/top_level.txt
mdconvertor_tools-0.0.5.dist-info/RECORD
