Metadata-Version: 2.1
Name: mdconvertor-tools
Version: 0.0.5
Summary: convertor is a simple and easy to use library for converting markdown files to various formats.
Home-page: https://github.com/codeperfectplus/mdconvertor-tools
Author: Deepak Raj
Author-email: deepak008@live.com
Project-URL: Documentation, https://mdconvertor-tools.readthedocs.io/en/latest/
Project-URL: Source, https://github.com/codeperfectplus/mdconvertor-tools
Project-URL: Tracker, https://github.com/codeperfectplus/mdconvertor-tools/issues
Classifier: Development Status :: 5 - Production/Stable
Classifier: Programming Language :: Python :: 3
Classifier: License :: OSI Approved :: Apache Software License
Classifier: Operating System :: OS Independent
Classifier: Intended Audience :: Developers
Requires-Python: >=3.6
License-File: LICENSE
Requires-Dist: bs4
Requires-Dist: markdown
